{
  "mp3c": {
    "checklistWidth": 8,
    "checklistLayout": [
      {
        "lookupId": 2,
        "value": 0,
        "start": 1,
        "max": 1,
        "segments": []
      },
      {
        "lookupId": 4,
        "value": 0,
        "start": 1,
        "max": 1,
        "segments": []
      },
      {
        "lookupId": 15,
        "value": 1,
        "start": 0,
        "max": 1,
        "segments": []
      },
      {
        "lookupId": 23,
        "value": 1,
        "start": 0,
        "max": 1,
        "segments": [],
        "over": "F_Boss",
        "overText": "Ghor Defeated"
      },
      {
        "lookupId": 33,
        "value": 1,
        "start": 0,
        "max": 1,
        "segments": [],
        "over": "Z_Orb",
        "overText": "Mining Laser Defeated"
      },
      {
        "lookupId": 1,
        "value": 0,
        "start": 1,
        "max": 1,
        "segments": []
      },
      {
        "lookupId": 14,
        "value": 0,
        "start": 0,
        "max": 1,
        "segments": []
      },
      {
        "lookupId": 8,
        "value": 0,
        "start": 1,
        "max": 1,
        "segments": []
      },
      {
        "lookupId": 9,
        "value": 1,
        "start": 0,
        "max": 1,
        "segments": []
      },
      {
        "lookupId": 18,
        "value": 1,
        "start": 0,
        "max": 1,
        "segments": [],
        "over": "F_Boss",
        "overText": "Rundas Defeated"
      },
      {
        "lookupId": 26,
        "value": 1,
        "start": 0,
        "max": 1,
        "segments": [],
        "over": "Z_Orb",
        "overText": "Skytown - Eastern Skytown - Xenoresearch B"
      },
      {
        "lookupId": 19,
        "value": 1,
        "start": 0,
        "max": 1,
        "segments": [],
        "over": "Z_Orb",
        "overText": "Bryyo - Hangar Bay"
      },
      {
        "lookupId": 28,
        "value": 1,
        "start": 0,
        "max": 1,
        "segments": [],
        "over": "F_Boss",
        "overText": "Helios Defeated"
      },
      {
        "lookupId": 3,
        "value": 0,
        "start": 1,
        "max": 1,
        "segments": []
      },
      {
        "lookupId": 17,
        "value": 0,
        "start": 0,
        "max": 1,
        "segments": []
      },
      {
        "lookupId": 24,
        "value": 1,
        "start": 0,
        "max": 1,
        "segments": [],
        "over": "Z_Orb",
        "overText": "Bryyo - Bryyo Ice - Hall of Remembrance"
      },
      {
        "lookupId": 5,
        "value": 0,
        "start": 1,
        "max": 1,
        "segments": []
      },
      {
        "lookupId": 6,
        "value": 0,
        "start": 1,
        "max": 1,
        "segments": []
      },
      {
        "lookupId": 22,
        "value": 1,
        "start": 0,
        "max": 1,
        "segments": [],
        "over": "F_Boss",
        "overText": "Defense Drone Defeated"
      },
      {
        "lookupId": 31,
        "value": 1,
        "start": 0,
        "max": 1,
        "segments": [],
        "over": "Z_Orb",
        "overText": "Skytown - Powerworks"
      },
      {
        "lookupId": 21,
        "value": 1,
        "start": 0,
        "max": 1,
        "segments": [],
        "over": "F_Boss",
        "overText": "Mogenar Defeated"
      },
      {
        "lookupId": 13,
        "value": 0,
        "start": 0,
        "max": 1,
        "segments": []
      },
      {
        "lookupId": 32,
        "value": 1,
        "start": 0,
        "max": 1,
        "segments": [],
        "over": "Z_Orb",
        "overText": "Pirate Homeworld - Pirate Research - Craneyard"
      },
      {
        "lookupId": -1,
        "value": 0,
        "start": 0,
        "max": 0,
        "segments": []
      },
      {
        "lookupId": 12,
        "value": 1,
        "start": 0,
        "max": 1,
        "segments": [],
        "over": "Z_Orb",
        "overText": "Norion - Docking Hub Alpha"
      },
      {
        "lookupId": 16,
        "value": 1,
        "start": 0,
        "max": 1,
        "segments": [],
        "over": "Z_Orb",
        "overText": "Bryyo - Reliquary I"
      },
      {
        "lookupId": 30,
        "value": 1,
        "start": 0,
        "max": 1,
        "segments": [],
        "over": "F_Boss",
        "overText": "Gandrayda Defeated"
      },
      {
        "lookupId": 25,
        "value": 1,
        "start": 0,
        "max": 1,
        "segments": [],
        "over": "Z_Orb",
        "overText": "Skytown - Eastern Skytown - Skytown Federation Landing Site"
      },
      {
        "lookupId": 34,
        "value": 1,
        "start": 0,
        "max": 1,
        "segments": [],
        "over": "F_Boss",
        "overText": "Omega Ridley Defeated"
      },
      {
        "lookupId": 29,
        "value": 1,
        "start": 0,
        "max": 1,
        "segments": [],
        "over": "Z_Orb",
        "overText": "Pirate Homeworld - Pirate Command - Command Vault"
      },
      {
        "lookupId": -1,
        "value": 0,
        "start": 0,
        "max": 0,
        "segments": []
      },
      {
        "lookupId": -1,
        "value": 0,
        "start": 0,
        "max": 0,
        "segments": []
      },
      {
        "lookupId": 11,
        "value": 1,
        "start": 0,
        "max": 14,
        "segments": []
      },
      {
        "lookupId": 10,
        "value": 1,
        "start": 0,
        "max": 50,
        "segments": []
      },
      {
        "lookupId": 20,
        "value": 1,
        "start": 0,
        "max": 8,
        "segments": []
      },
      {
        "lookupId": -1,
        "value": 0,
        "start": 0,
        "max": 0,
        "segments": []
      },
      {
        "lookupId": -1,
        "value": 0,
        "start": 0,
        "max": 0,
        "segments": []
      },
      {
        "lookupId": 27,
        "value": 0,
        "start": 0,
        "max": 3,
        "segments": []
      },
      {
        "lookupId": -1,
        "value": 0,
        "start": 0,
        "max": 0,
        "segments": [],
        "clearIfScramble": true
      },
      {
        "name": "",
        "value": 1,
        "start": 0,
        "max": 9,
        "segments": [
          {
            "lookupId": 35,
            "value": 1,
            "start": 0,
            "max": 9,
            "over": "C_Fuse",
            "overText": "Hints Acquired"
          },
          {
            "lookupId": 36,
            "value": 0,
            "start": 0,
            "max": 1,
            "clearIfScramble": true
          },
          {
            "lookupId": 1201,
            "value": 0,
            "start": 0,
            "max": 1,
            "clearIfScramble": true
          }
        ]
      },
      {
        "lookupId": 36,
        "value": 0,
        "start": 0,
        "max": 1,
        "segments": [],
        "displayIfScramble": true
      }
    ],
    "items": [
      {
        "id": "combatVisor",
        "name": "Combat Visor",
        "bg": "80d0ff",
        "itemId": 1,
        "nodeType": "upgrade"
      },
      {
        "id": "powerBeamA",
        "name": "Power Beam",
        "bg": "ffb508",
        "itemId": 2,
        "nodeType": "upgrade"
      },
      {
        "id": "scanVisorB",
        "name": "Scan Visor",
        "bg": "bca470",
        "itemId": 3,
        "nodeType": "upgrade"
      },
      {
        "id": "chargeBeam",
        "locale": {
          "enUS": {
            "id": "chargeBeamE"
          }
        },
        "name": "Charge Beam",
        "bg": "808000",
        "itemId": 4,
        "nodeType": "upgrade"
      },
      {
        "id": "morphBall",
        "name": "Morph Ball",
        "bg": "d8a480",
        "itemId": 5,
        "nodeType": "upgrade"
      },
      {
        "id": "bombC",
        "name": "Bombs",
        "bg": "3800a8",
        "itemId": 6,
        "nodeType": "upgrade"
      },
      {
        "id": "springBallA",
        "name": "Spring Ball",
        "bg": "886848",
        "itemId": 7,
        "nodeType": "upgrade"
      },
      {
        "id": "spinBoost",
        "name": "Space Jump Boots",
        "bg": "00a0e0",
        "itemId": 8,
        "nodeType": "upgrade"
      },
      {
        "id": "missileC",
        "name": "Missile Launcher",
        "bg": "d82800",
        "itemId": 9,
        "nodeType": "upgrade"
      },
      {
        "id": "missileTank",
        "name": "Missile Expansions",
        "singleItemName": "Missile Expansion",
        "alreadyHasMainItem": true,
        "bg": "d82800",
        "itemId": 10,
        "nodeType": "expansion"
      },
      {
        "id": "energyTankA",
        "name": "Energy Tanks",
        "singleItemName": "Energy Tank",
        "bg": "78a4bc",
        "itemId": 11,
        "nodeType": "expansion"
      },
      {
        "id": "grappleLasso",
        "name": "Grapple Lasso",
        "bg": "ff7b7b",
        "itemId": 12,
        "nodeType": "upgrade"
      },
      {
        "id": "commandVisor",
        "name": "Command Visor",
        "bg": "bfbf00",
        "itemId": 13,
        "nodeType": "upgrade"
      },
      {
        "id": "ped",
        "name": "P.E.D. Suit",
        "bg": "886848",
        "itemId": 14,
        "nodeType": "upgrade"
      },
      {
        "id": "hypermode",
        "locale": {
          "enUS": {
            "id": "hyperBeam"
          }
        },
        "name": "Hyper Beam",
        "bg": "1010e0",
        "itemId": 15,
        "nodeType": "upgrade"
      },
      {
        "id": "grappleBeam",
        "name": "Grapple Swing",
        "bg": "00e8d8",
        "itemId": 16,
        "nodeType": "upgrade"
      },
      {
        "id": "phazonSuit",
        "name": "Corrupted Hypermode",
        "bg": "282018",
        "itemId": 17,
        "nodeType": "upgrade"
      },
      {
        "id": "iceMissileA",
        "name": "Ice Missile",
        "bg": "2038ec",
        "itemId": 18,
        "nodeType": "upgrade"
      },
      {
        "id": "shipMissile",
        "name": "Ship Missile",
        "bg": "7f2800",
        "itemId": 19,
        "nodeType": "upgrade"
      },
      {
        "id": "shipMissileExpansion",
        "name": "Ship Missile Expansions",
        "singleItemName": "Ship Missile Expansion",
        "alreadyHasMainItem": true,
        "bg": "7f2800",
        "itemId": 20,
        "nodeType": "expansion"
      },
      {
        "id": "hyperBall",
        "name": "Hyper Ball",
        "bg": "98b830",
        "itemId": 21,
        "nodeType": "upgrade"
      },
      {
        "id": "boostBall",
        "name": "Boost Ball",
        "bg": "ff0094",
        "itemId": 22,
        "nodeType": "upgrade"
      },
      {
        "id": "flameShot",
        "locale": {
          "enUS": {
            "id": "plasmaBeamD"
          }
        },
        "name": "Plasma Beam",
        "bg": "ff4a4a",
        "itemId": 23,
        "nodeType": "upgrade"
      },
      {
        "id": "screwAttackA",
        "name": "Screw Attack",
        "bg": "69cd69",
        "itemId": 24,
        "nodeType": "upgrade"
      },
      {
        "id": "shipGrapple",
        "name": "Ship Grapple",
        "bg": "c0a8d8",
        "itemId": 25,
        "nodeType": "upgrade"
      },
      {
        "id": "seekerLauncherB",
        "name": "Seeker Launcher",
        "bg": "644080",
        "itemId": 26,
        "nodeType": "upgrade"
      },
      {
        "id": "theronianBomb",
        "name": "Theronian Bomb Components",
        "singleItemName": "Theronian Bomb Component",
        "bg": "ac842f",
        "itemId": 27,
        "nodeType": "expansion"
      },
      {
        "id": "hyperMissile",
        "name": "Hyper Missile",
        "bg": "007f0e",
        "itemId": 28,
        "nodeType": "upgrade"
      },
      {
        "id": "corruptionXRayVisor",
        "name": "X-Ray Visor",
        "bg": "c8d8d8",
        "itemId": 29,
        "nodeType": "upgrade"
      },
      {
        "id": "grappleVoltage",
        "name": "Grapple Voltage",
        "bg": "92278f",
        "itemId": 30,
        "nodeType": "upgrade"
      },
      {
        "id": "spiderBallA",
        "name": "Spider Ball",
        "bg": "007f0e",
        "itemId": 31,
        "nodeType": "upgrade"
      },
      {
        "id": "hazardShield",
        "name": "Hazard Shield",
        "bg": "602880",
        "itemId": 32,
        "nodeType": "upgrade"
      },
      {
        "id": "novaBeamA",
        "locale": {
          "enUS": {
            "id": "novaBeam"
          }
        },
        "name": "Nova Beam",
        "bg": "00ff08",
        "itemId": 33,
        "nodeType": "upgrade"
      },
      {
        "id": "hyperGrapple",
        "name": "Hyper Grapple",
        "bg": "fcc4d8",
        "itemId": 34,
        "nodeType": "upgrade"
      },
      {
        "id": "energyCell",
        "name": "Energy Cells",
        "singleItemName": "Energy Cell",
        "bg": "008080",
        "itemId": 35,
        "nodeType": "artifact"
      },
      {
        "id": "pirateCode",
        "name": "Pirate Code",
        "bg": "ce6665",
        "itemId": 36,
        "nodeType": "artifact"
      }
    ],
    "bosses": [
      {
        "id": "berserkerlorda",
        "name": "Berserker Lord",
        "bossId": 101
      },
      {
        "id": "mridley",
        "name": "Meta Ridley",
        "bossId": 102
      },
      {
        "id": "rundas",
        "name": "Rundas",
        "bossId": 103
      },
      {
        "id": "korakk",
        "name": "Pirate Hussar & Korakk Beast",
        "bossId": 104
      },
      {
        "id": "mogenar",
        "name": "Mogenar",
        "bossId": 105,
        "requires": [
          "5x1",
          "6x1",
          "15x1"
        ]
      },
      {
        "id": "steamlorda",
        "name": "Steamlord",
        "bossId": 106
      },
      {
        "id": "steamlordb",
        "name": "Steamlord",
        "bossId": 107
      },
      {
        "id": "steamlordc",
        "name": "Steamlord",
        "bossId": 108
      },
      {
        "id": "defdrone",
        "name": "Defense Drone",
        "bossId": 109,
        "requires": [
          "15x1"
        ]
      },
      {
        "id": "ghor",
        "name": "Ghor",
        "bossId": 110
      },
      {
        "id": "berserkerlordb",
        "name": "Berserker Lord",
        "bossId": 111
      },
      {
        "id": "helios",
        "name": "Helios",
        "bossId": 112,
        "requires": [
          "15x1"
        ]
      },
      {
        "id": "gandrayda",
        "name": "Gandrayda",
        "bossId": 113
      },
      {
        "id": "mhatchera",
        "name": "Metroid Hatcher",
        "bossId": 114
      },
      {
        "id": "mhatcherb",
        "name": "Metroid Hatcher",
        "bossId": 115
      },
      {
        "id": "mhatcherc",
        "name": "Metroid Hatcher",
        "bossId": 116
      },
      {
        "id": "phharvester",
        "name": "Phazon Harvester",
        "bossId": 118,
        "requires": [
          "19x1",
          "120x1"
        ]
      },
      {
        "id": "pircommander",
        "name": "Pirate Commander",
        "bossId": 119
      },
      {
        "id": "oridley",
        "name": "Omega Ridley",
        "bossId": 120,
        "requires": [
          "15x1",
          "29x1",
          "33x1"
        ]
      },
      {
        "id": "levinfant",
        "name": "Leviathan Infant",
        "bossId": 121,
        "requires": [
          "15x1"
        ]
      },
      {
        "id": "dsamusd",
        "name": "Dark Samus",
        "bossId": 122,
        "requires": [
          "15x1"
        ]
      },
      {
        "id": "au313",
        "name": "Aurora Unit 313",
        "bossId": 123,
        "requires": [
          "15x1"
        ]
      }
    ],
    "areas": [
      {
        "id": 1,
        "name": "GFS Olympus",
        "hasGameStart": true,
        "color": "2038ec"
      },
      {
        "id": 2,
        "name": "GFS Olympus 2",
        "color": "2038ec"
      },
      {
        "id": 3,
        "name": "Norion",
        "color": "db2b00"
      },
      {
        "id": 4,
        "name": "Bryyo - Cliffside",
        "color": "009700"
      },
      {
        "id": 5,
        "name": "Bryyo - Fire",
        "color": "009700"
      },
      {
        "id": 6,
        "name": "Bryyo - Thorn Jungle",
        "color": "009700"
      },
      {
        "id": 7,
        "name": "Bryyo - Ice",
        "color": "009700"
      },
      {
        "id": 8,
        "name": "Bryyo - Seed",
        "color": "009700"
      },
      {
        "id": 9,
        "name": "Elysia - Skytown West",
        "color": "bf00bf"
      },
      {
        "id": 10,
        "name": "Elysia - Skytown East",
        "color": "bf00bf"
      },
      {
        "id": 11,
        "name": "Elysia - Seed",
        "color": "bf00bf"
      },
      {
        "id": 12,
        "name": "GFS Valhalla",
        "color": "2038ec"
      },
      {
        "id": 13,
        "name": "Pirate Homeworld - Command Center",
        "color": "bcbcbc"
      },
      {
        "id": 14,
        "name": "Pirate Homeworld - Research",
        "color": "bcbcbc"
      },
      {
        "id": 15,
        "name": "Pirate Homeworld - Phazon Mines",
        "color": "bcbcbc"
      },
      {
        "id": 16,
        "name": "Pirate Homeworld - Seed",
        "color": "bcbcbc"
      },
      {
        "id": 17,
        "name": "Phaaze",
        "color": "db2b00"
      }
    ],
    "extras": [
      {
        "id": "unused",
        "name": "First Mission",
        "extraId": 1101,
        "nodeType": "event",
        "bg": "5298bc"
      },
      {
        "id": "unused",
        "name": "Mission Briefing",
        "extraId": 1102,
        "nodeType": "event",
        "bg": "5298bc"
      },
      {
        "id": "energyCell",
        "name": "Lab Energy Cell",
        "extraId": 1103,
        "nodeType": "event",
        "bg": "5298bc"
      },
      {
        "id": "saveRoom",
        "name": "Save Event 1",
        "extraId": 1104,
        "nodeType": "trigger",
        "bg": "5298bc"
      },
      {
        "id": "norion",
        "name": "Dock A Access",
        "extraId": 1111,
        "nodeType": "trigger",
        "bg": "5298bc"
      },
      {
        "id": "norion",
        "name": "Dock B Access",
        "extraId": 1112,
        "nodeType": "trigger",
        "bg": "5298bc"
      },
      {
        "id": "norion",
        "name": "Generator A Online",
        "extraId": 1113,
        "nodeType": "event",
        "bg": "5298bc"
      },
      {
        "id": "norion",
        "name": "Generator B Online",
        "extraId": 1114,
        "nodeType": "event",
        "bg": "5298bc"
      },
      {
        "id": "norion",
        "name": "Generator C Online",
        "extraId": 1115,
        "nodeType": "event",
        "bg": "5298bc"
      },
      {
        "id": "saveRoom",
        "name": "Save Event 2",
        "extraId": 1105,
        "nodeType": "trigger",
        "bg": "5298bc"
      },
      {
        "id": "bryyo",
        "name": "Bryyo Mission",
        "extraId": 1106,
        "nodeType": "event",
        "bg": "6d9b6d"
      },
      {
        "id": "bryyo",
        "name": "Fed Dock",
        "extraId": 1121,
        "nodeType": "trigger",
        "bg": "6d9b6d"
      },
      {
        "id": "bryyo",
        "name": "Fire Access",
        "extraId": 1122,
        "nodeType": "trigger",
        "bg": "6d9b6d"
      },
      {
        "id": "bryyo",
        "name": "Thorn Jungle Access",
        "extraId": 1123,
        "nodeType": "trigger",
        "bg": "6d9b6d"
      },
      {
        "id": "bryyo",
        "name": "Shield Generator 1 Destroyed",
        "extraId": 1124,
        "nodeType": "trigger",
        "bg": "6d9b6d"
      },
      {
        "id": "bryyo",
        "name": "Turret 1 Destroyed",
        "extraId": 1125,
        "nodeType": "trigger",
        "bg": "6d9b6d"
      },
      {
        "id": "bryyo",
        "name": "Turret 2 Destroyed",
        "extraId": 1126,
        "nodeType": "trigger",
        "bg": "6d9b6d"
      },
      {
        "id": "bryyo",
        "name": "Shield Generator 2 Destroyed",
        "extraId": 1127,
        "nodeType": "trigger",
        "bg": "6d9b6d"
      },
      {
        "id": "bryyo",
        "name": "Hidden Court Grapple",
        "extraId": 1128,
        "nodeType": "trigger",
        "bg": "6d9b6d"
      },
      {
        "id": "bryyo",
        "name": "Bridge Access A",
        "extraId": 1129,
        "nodeType": "trigger",
        "bg": "6d9b6d"
      },
      {
        "id": "bryyo",
        "name": "Bridge Access B",
        "extraId": 1130,
        "nodeType": "trigger",
        "bg": "6d9b6d"
      },
      {
        "id": "unused",
        "name": "Valhalla Access",
        "extraId": 1131,
        "nodeType": "event",
        "bg": "ce6665"
      },
      {
        "id": "elysia",
        "name": "Ghor Assault",
        "extraId": 1141,
        "nodeType": "trigger",
        "bg": "ac842f"
      },
      {
        "id": "elysia",
        "name": "AU 217 Online",
        "extraId": 1142,
        "nodeType": "trigger",
        "bg": "ac842f"
      },
      {
        "id": "elysia",
        "name": "Site A Access",
        "extraId": 1143,
        "nodeType": "trigger",
        "bg": "ac842f"
      },
      {
        "id": "elysia",
        "name": "Site B Access",
        "extraId": 1144,
        "nodeType": "trigger",
        "bg": "ac842f"
      },
      {
        "id": "xenoresearch",
        "name": "Xenoresearch Cells Open",
        "extraId": 1145,
        "nodeType": "trigger",
        "bg": "ac842f"
      },
      {
        "id": "elysia",
        "name": "Shield Nuked",
        "extraId": 1146,
        "nodeType": "trigger",
        "bg": "ac842f"
      },
      {
        "id": "elysia",
        "name": "Escape Pod",
        "extraId": 1147,
        "nodeType": "trigger",
        "bg": "ac842f"
      },
      {
        "id": "elysia",
        "name": "Pirate Homeworld Access",
        "extraId": 1151,
        "nodeType": "event",
        "bg": "b7746e"
      },
      {
        "id": "urtraghus",
        "name": "Fans Off",
        "extraId": 1152,
        "nodeType": "trigger",
        "bg": "b7746e"
      },
      {
        "id": "urtraghus",
        "name": "Shield Core Sighted",
        "extraId": 1153,
        "nodeType": "event",
        "bg": "b7746e"
      },
      {
        "id": "urtraghus",
        "name": "Rescue Mission",
        "extraId": 1154,
        "nodeType": "event",
        "bg": "b7746e"
      },
      {
        "id": "urtraghus",
        "name": "Access to Research",
        "extraId": 1155,
        "nodeType": "trigger",
        "bg": "b7746e"
      },
      {
        "id": "urtraghus",
        "name": "Scrap Access",
        "extraId": 1156,
        "nodeType": "trigger",
        "bg": "b7746e"
      },
      {
        "id": "urtraghus",
        "name": "Mines Unlocked",
        "extraId": 1157,
        "nodeType": "trigger",
        "bg": "b7746e"
      },
      {
        "id": "urtraghus",
        "name": "Metroids Loose",
        "extraId": 1158,
        "nodeType": "trigger",
        "bg": "b7746e"
      },
      {
        "id": "unused",
        "name": "Dread Reference",
        "extraId": 1159,
        "nodeType": "easter",
        "bg": "b7746e"
      },
      {
        "id": "urtraghus",
        "name": "Mine Loop Open",
        "extraId": 1160,
        "nodeType": "trigger",
        "bg": "b7746e"
      },
      {
        "id": "urtraghus",
        "name": "Shield Core Down",
        "extraId": 1161,
        "nodeType": "trigger",
        "bg": "b7746e"
      },
      {
        "id": "urtraghus",
        "name": "Transit Tunnels",
        "extraId": 1162,
        "nodeType": "event",
        "bg": "b7746e"
      },
      {
        "id": "urtraghus",
        "name": "Seed Door",
        "extraId": 1163,
        "nodeType": "trigger",
        "bg": "b7746e"
      },
      {
        "id": "unused",
        "name": "AU 313 Pad Code",
        "extraId": 1171,
        "nodeType": "easter",
        "bg": "ce6665"
      },
      {
        "id": "unused",
        "name": "AU 313 Message",
        "extraId": 1172,
        "nodeType": "easter",
        "bg": "ce6665"
      },
      {
        "id": "phaaze",
        "name": "Phaaze accessible",
        "extraId": 1201,
        "nodeType": "event",
        "bg": "35a0d8"
      },
      {
        "id": "saveRoom",
        "name": "Save Station",
        "extraId": 1001,
        "nodeType": "save"
      },
      {
        "id": "unused",
        "name": "Gunship",
        "extraId": 1002,
        "nodeType": "save"
      },
      {
        "id": "unused",
        "name": "Map: Norion",
        "extraId": 1003,
        "nodeType": "map"
      },
      {
        "id": "unused",
        "name": "Map: Bryyo",
        "extraId": 1004,
        "nodeType": "map"
      },
      {
        "id": "unused",
        "name": "Map: Skytown West",
        "extraId": 1005,
        "nodeType": "map"
      },
      {
        "id": "unused",
        "name": "Map: Skytown East",
        "extraId": 1006,
        "nodeType": "map"
      },
      {
        "id": "unused",
        "name": "Map: Norion Clues",
        "extraId": 1007,
        "nodeType": "map"
      },
      {
        "id": "unused",
        "name": "Map: Bryyo Clues",
        "extraId": 1008,
        "nodeType": "map"
      },
      {
        "id": "unused",
        "name": "Map: Elysia Clues",
        "extraId": 1009,
        "nodeType": "map"
      },
      {
        "id": "unused",
        "name": "Map: Pirate Homeworld Clues",
        "extraId": 1010,
        "nodeType": "map"
      },
      {
        "id": "unused",
        "name": "Map: Pirate Homeworld Command & Research",
        "extraId": 1011,
        "nodeType": "map"
      },
      {
        "id": "golemHead",
        "name": "Golem Head",
        "extraId": 1021,
        "nodeType": "slot"
      },
      {
        "id": "generator",
        "name": "Large Generator",
        "extraId": 1022,
        "nodeType": "slot"
      },
      {
        "id": "screwAttackB",
        "name": "Gold Credit",
        "extraId": 1023,
        "nodeType": "lore"
      }
    ],
    "mapTree": [
      {
        "hubId": 1,
        "nodeType": "start",
        "mapId": 1,
        "children": []
      }
    ],
    "grid": "mp_grid.png"
  }
}